ext/__init__.py
ext/NN/__init__.py
ext/NN/readme.md
ext/NN/Tensorflow/01_basics.py
ext/NN/Tensorflow/__init__.py
ext/NN/Torch/__init__.py
ext/NN/Torch/readme.md
ext/NN/Torch/utils.py
ext/NN/Torch/01_TASK/__init__.py
ext/NN/Torch/01_TASK/readme.md
ext/NN/Torch/02_TASK/__init__.py
ext/NN/Torch/02_TASK/nn.py
ext/NN/Torch/02_TASK/numpy_GB.py
ext/NN/Torch/02_TASK/pytorch_GM.py
ext/NN/Torch/02_TASK/readme.md
ext/NN/Torch/04_TASK/__init__.py
ext/NN/Torch/04_TASK/mlp.py
ext/NN/Torch/05_TASK/__init__.py
ext/NN/Torch/05_TASK/dropout.py
ext/NN/Torch/05_TASK/l1l2.py
ext/NN/datawhale_nlp/Day_01.ipynb
ext/NN/datawhale_nlp/Task_02.py
ext/NN/datawhale_nlp/Task_03.py
ext/NN/datawhale_nlp/Task_04_BayesSVM.py
ext/NN/datawhale_nlp/Task_04_LDAPSI.py
ext/NN/datawhale_nlp/Task_05_NN.md
ext/NN/datawhale_nlp/Task_06_FastText.md
ext/NN/datawhale_nlp/Task_07_CNN.md
ext/NN/datawhale_nlp/Task_08_RNN.md
ext/NN/datawhale_nlp/Task_09_Attention.md
ext/NN/datawhale_nlp/Task_10_Bert.md
ext/NN/datawhale_nlp/__init__.py
ext/NN/datawhale_nlp/pred.csv
ext/NN/datawhale_nlp/readme.md
ext/NN/datawhale_nlp/test.csv
ext/NN/datawhale_nlp/train.csv
"ext/Xmind/Interview
.xmind"
ext/Xmind/ML.xmind
ext/Xmind/__init__.py
ext/Xmind/baseKnowledge.xmind
ext/Xmind/featuretools.xmind
ext/Xmind/modelPipline.xmind
tql/TODO.md
tql/__init__.py
tql/pipe.py
tql/crawler/HotSpider.py
tql/crawler/README.md
tql/crawler/XPATH.md
tql/crawler/__init__.py
tql/crawler/daily.py
tql/crawler/demo.py
tql/crawler/hotnews.py
tql/crawler/proxies.py
tql/crawler/utils.py
tql/crawler/scrapy/__init__.py
tql/crawler/selenium/__init__.py
tql/crawler/selenium/demo.py
tql/eda/DataFrameSummary.py
tql/eda/README.md
tql/eda/SimpleEDA.py
tql/eda/__init__.py
tql/features/README.md
tql/features/__init__.py
tql/features/agg/Funcs.py
tql/features/agg/GroupFeats.py
tql/features/agg/RowFeats.py
tql/features/agg/__init__.py
tql/features/cat/VecFeats.py
tql/features/cat/__init__.py
tql_Python-0.0.1560759418.dist-info/METADATA
tql_Python-0.0.1560759418.dist-info/RECORD
tql_Python-0.0.1560759418.dist-info/WHEEL
tql_Python-0.0.1560759418.dist-info/top_level.txt
